webarticlecurator/__init__.py
webarticlecurator/__main__.py
webarticlecurator/crawl_schema.yaml
webarticlecurator/enhanced_downloader.py
webarticlecurator/news_crawler.py
webarticlecurator/other_modes.py
webarticlecurator/site_schema.yaml
webarticlecurator/strategies.py
webarticlecurator/utils.py
webarticlecurator/version.py
webarticlecurator-1.13.0.dist-info/LICENSE
webarticlecurator-1.13.0.dist-info/METADATA
webarticlecurator-1.13.0.dist-info/WHEEL
webarticlecurator-1.13.0.dist-info/entry_points.txt
webarticlecurator-1.13.0.dist-info/RECORD
