Metadata-Version: 2.1
Name: webarticlecurator
Version: 1.13.0
Summary: A crawler program to download content from portals (news, forums, blogs) and convert it to the desired output format according to the configuration.
Home-page: https://github.com/ELTE-DH/WebArticleCurator
License: LGPLv3
Author: dlazesz
Requires-Python: >=3.8,<4.0
Classifier: Development Status :: 5 - Production/Stable
Classifier: License :: Other/Proprietary License
Classifier: Operating System :: OS Independent
Classifier: Programming Language :: Python :: 3
Classifier: Programming Language :: Python :: 3.8
Classifier: Programming Language :: Python :: 3.9
Classifier: Programming Language :: Python :: 3.10
Classifier: Programming Language :: Python :: 3.11
Classifier: Programming Language :: Python :: 3.12
Classifier: Topic :: Software Development :: Libraries :: Python Modules
Provides-Extra: full
Provides-Extra: newspaper3k
Requires-Dist: beautifulsoup4 (>=4.12.3,<5.0.0)
Requires-Dist: chardet (>=5.2.0,<6.0.0)
Requires-Dist: lxml (>=5.3.0,<6.0.0)
Requires-Dist: mplogger (>=1.1.0,<2.0.0)
Requires-Dist: newspaper3k (>=0.2.8,<0.3.0) ; extra == "newspaper3k" or extra == "full"
Requires-Dist: pyyaml (>=6.0.2,<7.0.0)
Requires-Dist: ratelimit (>=2.2.1,<3.0.0)
Requires-Dist: requests (>=2.32.3,<3.0.0)
Requires-Dist: urllib3 (>=2.2.3,<3.0.0)
Requires-Dist: warcio (>=1.7.0,<2.0.0)
Requires-Dist: yamale (>=5.2.1,<6.0.0)
Project-URL: Repository, https://github.com/ELTE-DH/WebArticleCurator
